asyncmd/__init__.py
asyncmd/_config.py
asyncmd/_version.py
asyncmd/config.py
asyncmd/mdconfig.py
asyncmd/mdengine.py
asyncmd/py.typed
asyncmd/tools.py
asyncmd/utils.py
asyncmd/gromacs/__init__.py
asyncmd/gromacs/mdconfig.py
asyncmd/gromacs/mdengine.py
asyncmd/gromacs/utils.py
asyncmd/slurm/__init__.py
asyncmd/slurm/cluster_mediator.py
asyncmd/slurm/config.py
asyncmd/slurm/constants_and_errors.py
asyncmd/slurm/process.py
asyncmd/trajectory/__init__.py
asyncmd/trajectory/convert.py
asyncmd/trajectory/functionwrapper.py
asyncmd/trajectory/propagate.py
asyncmd/trajectory/trajectory.py
asyncmd/trajectory/trajectory_cache.py
asyncmd-0.4.1.dist-info/licenses/LICENSE
asyncmd-0.4.1.dist-info/METADATA
asyncmd-0.4.1.dist-info/WHEEL
asyncmd-0.4.1.dist-info/top_level.txt
asyncmd-0.4.1.dist-info/RECORD
