Metadata-Version: 2.4
Name: asyncmd
Version: 0.4.1
Summary: asyncmd is a library to write concurrent code to run and analyze molecular dynamics simulations using pythons async/await syntax.
Author-email: Hendrik Jung <hendrik.jung@biophys.mpg.de>
Maintainer-email: Hendrik Jung <hendrik.jung@biophys.mpg.de>
Project-URL: Documentation, https://asyncmd.readthedocs.io/en/latest/
Project-URL: Repository, https://github.com/bio-phys/asyncmd.git
Project-URL: Issues, https://github.com/bio-phys/asyncmd/issues
Keywords: molecular dynamics,molecular-dynamics,MD,high performance computing,HPC,slurm,SLURM,gromacs,GROMACS
Classifier: Development Status :: 4 - Beta
Classifier: Intended Audience :: Science/Research
Classifier: Natural Language :: English
Classifier: License :: OSI Approved :: GNU General Public License v3 or later (GPLv3+)
Classifier: Operating System :: OS Independent
Classifier: Programming Language :: Python
Classifier: Programming Language :: Python :: 3
Classifier: Topic :: Scientific/Engineering
Classifier: Topic :: Scientific/Engineering :: Chemistry
Classifier: Topic :: Scientific/Engineering :: Physics
Classifier: Topic :: Software Development :: Libraries :: Python Modules
Requires-Python: >=3.10
License-File: LICENSE
Requires-Dist: aiofiles
Requires-Dist: mdanalysis
Requires-Dist: numpy
Requires-Dist: scipy
Provides-Extra: docs
Requires-Dist: sphinx; extra == "docs"
Requires-Dist: myst-nb; extra == "docs"
Requires-Dist: sphinx-book-theme; extra == "docs"
Provides-Extra: tests
Requires-Dist: pytest; extra == "tests"
Requires-Dist: pytest-asyncio; extra == "tests"
Provides-Extra: tests-all
Requires-Dist: asyncmd[tests]; extra == "tests-all"
Requires-Dist: h5py; extra == "tests-all"
Requires-Dist: coverage; extra == "tests-all"
Requires-Dist: pytest-cov; extra == "tests-all"
Provides-Extra: dev
Requires-Dist: asyncmd[docs,tests-all]; extra == "dev"
Requires-Dist: jupyterlab; extra == "dev"
Requires-Dist: ipywidgets; extra == "dev"
Requires-Dist: tqdm; extra == "dev"
Requires-Dist: pylint; extra == "dev"
Dynamic: license-file
